{
  "biodata": {
    "associated_names": [
      "Long Beach Marine Stadium"
    ],
    "place": "Long Beach, California",
    "coordinates": "33.767502,-118.128624",
    "coordinates_trust": "Definitely here",
    "games": [
      {
        "year": "1932",
        "season": "Summer"
      }
    ],
    "sports": [
      "Rowing"
    ],
    "opened": "1925",
    "type": "outdoor venue"
  },
  "event_data": [
    [
      {
        "text": "1932 Summer Olympics",
        "link": "https://www.olympedia.org/editions/10"
      },
      {
        "text": "Rowing",
        "link": "https://www.olympedia.org/sports/ROW"
      },
      {
        "text": "Single Sculls, Men",
        "link": "https://www.olympedia.org/results/157882"
      },
      {
        "text": "9 – 13 August 1932"
      }
    ],
    [
      {
        "text": "1932 Summer Olympics",
        "link": "https://www.olympedia.org/editions/10"
      },
      {
        "text": "Rowing",
        "link": "https://www.olympedia.org/sports/ROW"
      },
      {
        "text": "Double Sculls, Men",
        "link": "https://www.olympedia.org/results/157889"
      },
      {
        "text": "9 – 13 August 1932"
      }
    ],
    [
      {
        "text": "1932 Summer Olympics",
        "link": "https://www.olympedia.org/editions/10"
      },
      {
        "text": "Rowing",
        "link": "https://www.olympedia.org/sports/ROW"
      },
      {
        "text": "Coxless Pairs, Men",
        "link": "https://www.olympedia.org/results/157896"
      },
      {
        "text": "10 – 13 August 1932"
      }
    ],
    [
      {
        "text": "1932 Summer Olympics",
        "link": "https://www.olympedia.org/editions/10"
      },
      {
        "text": "Rowing",
        "link": "https://www.olympedia.org/sports/ROW"
      },
      {
        "text": "Coxed Pairs, Men",
        "link": "https://www.olympedia.org/results/157903"
      },
      {
        "text": "13 August 1932"
      }
    ],
    [
      {
        "text": "1932 Summer Olympics",
        "link": "https://www.olympedia.org/editions/10"
      },
      {
        "text": "Rowing",
        "link": "https://www.olympedia.org/sports/ROW"
      },
      {
        "text": "Coxless Fours, Men",
        "link": "https://www.olympedia.org/results/157904"
      },
      {
        "text": "10 – 13 August 1932"
      }
    ],
    [
      {
        "text": "1932 Summer Olympics",
        "link": "https://www.olympedia.org/editions/10"
      },
      {
        "text": "Rowing",
        "link": "https://www.olympedia.org/sports/ROW"
      },
      {
        "text": "Coxed Fours, Men",
        "link": "https://www.olympedia.org/results/157911"
      },
      {
        "text": "10 – 13 August 1932"
      }
    ],
    [
      {
        "text": "1932 Summer Olympics",
        "link": "https://www.olympedia.org/editions/10"
      },
      {
        "text": "Rowing",
        "link": "https://www.olympedia.org/sports/ROW"
      },
      {
        "text": "Eights, Men",
        "link": "https://www.olympedia.org/results/157918"
      },
      {
        "text": "10 – 13 August 1932"
      }
    ]
  ]
}