{
  "biodata": {
    "associated_names": [
      "Stadio Olimpico",
      "Olympic Stadium",
      "Stadio dei Cipressi (1930-1950), Stadio dei Centomila (1950-1960)"
    ],
    "place": "Roma",
    "coordinates": "41.933886,12.454786",
    "coordinates_trust": "Definitely here",
    "year": "1960",
    "season": "Summer",
    "sports": [
      "Athletics",
      "Equestrian Jumping",
      "Opening ceremony",
      "Closing ceremony"
    ],
    "opened": "1937",
    "type": "outdoor venue",
    "dimensions": "400 m",
    "surface": "Loose cinders",
    "altitude": "34 m"
  },
  "event_data": [
    [
      {
        "text": "1960 Summer Olympics",
        "link": "https://www.olympedia.org/editions/15"
      },
      {
        "text": "Athletics",
        "link": "https://www.olympedia.org/sports/ATH"
      },
      {
        "text": "100 metres, Men",
        "link": "https://www.olympedia.org/results/59618"
      },
      {
        "text": "31 August –  1 September 1960"
      }
    ],
    [
      {
        "text": "1960 Summer Olympics",
        "link": "https://www.olympedia.org/editions/15"
      },
      {
        "text": "Athletics",
        "link": "https://www.olympedia.org/sports/ATH"
      },
      {
        "text": "200 metres, Men",
        "link": "https://www.olympedia.org/results/59638"
      },
      {
        "text": "2 –  3 September 1960"
      }
    ],
    [
      {
        "text": "1960 Summer Olympics",
        "link": "https://www.olympedia.org/editions/15"
      },
      {
        "text": "Athletics",
        "link": "https://www.olympedia.org/sports/ATH"
      },
      {
        "text": "400 metres, Men",
        "link": "https://www.olympedia.org/results/59661"
      },
      {
        "text": "3 –  6 September 1960"
      }
    ],
    [
      {
        "text": "1960 Summer Olympics",
        "link": "https://www.olympedia.org/editions/15"
      },
      {
        "text": "Athletics",
        "link": "https://www.olympedia.org/sports/ATH"
      },
      {
        "text": "800 metres, Men",
        "link": "https://www.olympedia.org/results/59681"
      },
      {
        "text": "31 August –  2 September 1960"
      }
    ],
    [
      {
        "text": "1960 Summer Olympics",
        "link": "https://www.olympedia.org/editions/15"
      },
      {
        "text": "Athletics",
        "link": "https://www.olympedia.org/sports/ATH"
      },
      {
        "text": "1,500 metres, Men",
        "link": "https://www.olympedia.org/results/59701"
      },
      {
        "text": "3 –  6 September 1960"
      }
    ],
    [
      {
        "text": "1960 Summer Olympics",
        "link": "https://www.olympedia.org/editions/15"
      },
      {
        "text": "Athletics",
        "link": "https://www.olympedia.org/sports/ATH"
      },
      {
        "text": "5,000 metres, Men",
        "link": "https://www.olympedia.org/results/59707"
      },
      {
        "text": "31 August –  2 September 1960"
      }
    ],
    [
      {
        "text": "1960 Summer Olympics",
        "link": "https://www.olympedia.org/editions/15"
      },
      {
        "text": "Athletics",
        "link": "https://www.olympedia.org/sports/ATH"
      },
      {
        "text": "10,000 metres, Men",
        "link": "https://www.olympedia.org/results/59714"
      },
      {
        "text": "8 September 1960"
      }
    ],
    [
      {
        "text": "1960 Summer Olympics",
        "link": "https://www.olympedia.org/editions/15"
      },
      {
        "text": "Athletics",
        "link": "https://www.olympedia.org/sports/ATH"
      },
      {
        "text": "110 metres Hurdles, Men",
        "link": "https://www.olympedia.org/results/59716"
      },
      {
        "text": "3 –  5 September 1960"
      }
    ],
    [
      {
        "text": "1960 Summer Olympics",
        "link": "https://www.olympedia.org/editions/15"
      },
      {
        "text": "Athletics",
        "link": "https://www.olympedia.org/sports/ATH"
      },
      {
        "text": "400 metres Hurdles, Men",
        "link": "https://www.olympedia.org/results/59733"
      },
      {
        "text": "31 August –  2 September 1960"
      }
    ],
    [
      {
        "text": "1960 Summer Olympics",
        "link": "https://www.olympedia.org/editions/15"
      },
      {
        "text": "Athletics",
        "link": "https://www.olympedia.org/sports/ATH"
      },
      {
        "text": "3,000 metres Steeplechase, Men",
        "link": "https://www.olympedia.org/results/59745"
      },
      {
        "text": "1 –  3 September 1960"
      }
    ],
    [
      {
        "text": "1960 Summer Olympics",
        "link": "https://www.olympedia.org/editions/15"
      },
      {
        "text": "Athletics",
        "link": "https://www.olympedia.org/sports/ATH"
      },
      {
        "text": "4 × 100 metres Relay, Men",
        "link": "https://www.olympedia.org/results/59753"
      },
      {
        "text": "7 –  8 September 1960"
      }
    ],
    [
      {
        "text": "1960 Summer Olympics",
        "link": "https://www.olympedia.org/editions/15"
      },
      {
        "text": "Athletics",
        "link": "https://www.olympedia.org/sports/ATH"
      },
      {
        "text": "4 × 400 metres Relay, Men",
        "link": "https://www.olympedia.org/results/59763"
      },
      {
        "text": "7 –  8 September 1960"
      }
    ],
    [
      {
        "text": "1960 Summer Olympics",
        "link": "https://www.olympedia.org/editions/15"
      },
      {
        "text": "Athletics",
        "link": "https://www.olympedia.org/sports/ATH"
      },
      {
        "text": "20 kilometres Race Walk, Men",
        "link": "https://www.olympedia.org/results/59751"
      },
      {
        "text": "2 September 1960"
      }
    ],
    [
      {
        "text": "1960 Summer Olympics",
        "link": "https://www.olympedia.org/editions/15"
      },
      {
        "text": "Athletics",
        "link": "https://www.olympedia.org/sports/ATH"
      },
      {
        "text": "50 kilometres Race Walk, Men",
        "link": "https://www.olympedia.org/results/59752"
      },
      {
        "text": "7 September 1960"
      }
    ],
    [
      {
        "text": "1960 Summer Olympics",
        "link": "https://www.olympedia.org/editions/15"
      },
      {
        "text": "Athletics",
        "link": "https://www.olympedia.org/sports/ATH"
      },
      {
        "text": "High Jump, Men",
        "link": "https://www.olympedia.org/results/59773"
      },
      {
        "text": "1 September 1960"
      }
    ],
    [
      {
        "text": "1960 Summer Olympics",
        "link": "https://www.olympedia.org/editions/15"
      },
      {
        "text": "Athletics",
        "link": "https://www.olympedia.org/sports/ATH"
      },
      {
        "text": "Pole Vault, Men",
        "link": "https://www.olympedia.org/results/59789"
      },
      {
        "text": "5 –  7 September 1960"
      }
    ],
    [
      {
        "text": "1960 Summer Olympics",
        "link": "https://www.olympedia.org/editions/15"
      },
      {
        "text": "Athletics",
        "link": "https://www.olympedia.org/sports/ATH"
      },
      {
        "text": "Long Jump, Men",
        "link": "https://www.olympedia.org/results/59806"
      },
      {
        "text": "2 September 1960"
      }
    ],
    [
      {
        "text": "1960 Summer Olympics",
        "link": "https://www.olympedia.org/editions/15"
      },
      {
        "text": "Athletics",
        "link": "https://www.olympedia.org/sports/ATH"
      },
      {
        "text": "Triple Jump, Men",
        "link": "https://www.olympedia.org/results/59827"
      },
      {
        "text": "6 September 1960"
      }
    ],
    [
      {
        "text": "1960 Summer Olympics",
        "link": "https://www.olympedia.org/editions/15"
      },
      {
        "text": "Athletics",
        "link": "https://www.olympedia.org/sports/ATH"
      },
      {
        "text": "Shot Put, Men",
        "link": "https://www.olympedia.org/results/59848"
      },
      {
        "text": "31 August 1960"
      }
    ],
    [
      {
        "text": "1960 Summer Olympics",
        "link": "https://www.olympedia.org/editions/15"
      },
      {
        "text": "Athletics",
        "link": "https://www.olympedia.org/sports/ATH"
      },
      {
        "text": "Discus Throw, Men",
        "link": "https://www.olympedia.org/results/59860"
      },
      {
        "text": "6 –  7 September 1960"
      }
    ],
    [
      {
        "text": "1960 Summer Olympics",
        "link": "https://www.olympedia.org/editions/15"
      },
      {
        "text": "Athletics",
        "link": "https://www.olympedia.org/sports/ATH"
      },
      {
        "text": "Hammer Throw, Men",
        "link": "https://www.olympedia.org/results/59877"
      },
      {
        "text": "2 –  3 September 1960"
      }
    ],
    [
      {
        "text": "1960 Summer Olympics",
        "link": "https://www.olympedia.org/editions/15"
      },
      {
        "text": "Athletics",
        "link": "https://www.olympedia.org/sports/ATH"
      },
      {
        "text": "Javelin Throw, Men",
        "link": "https://www.olympedia.org/results/59889"
      },
      {
        "text": "7 –  8 September 1960"
      }
    ],
    [
      {
        "text": "1960 Summer Olympics",
        "link": "https://www.olympedia.org/editions/15"
      },
      {
        "text": "Athletics",
        "link": "https://www.olympedia.org/sports/ATH"
      },
      {
        "text": "Decathlon, Men",
        "link": "https://www.olympedia.org/results/59906"
      },
      {
        "text": "5 –  6 September 1960"
      }
    ],
    [
      {
        "text": "1960 Summer Olympics",
        "link": "https://www.olympedia.org/editions/15"
      },
      {
        "text": "Athletics",
        "link": "https://www.olympedia.org/sports/ATH"
      },
      {
        "text": "100 metres, Women",
        "link": "https://www.olympedia.org/results/59952"
      },
      {
        "text": "1 –  2 September 1960"
      }
    ],
    [
      {
        "text": "1960 Summer Olympics",
        "link": "https://www.olympedia.org/editions/15"
      },
      {
        "text": "Athletics",
        "link": "https://www.olympedia.org/sports/ATH"
      },
      {
        "text": "200 metres, Women",
        "link": "https://www.olympedia.org/results/59970"
      },
      {
        "text": "3 –  5 September 1960"
      }
    ],
    [
      {
        "text": "1960 Summer Olympics",
        "link": "https://www.olympedia.org/editions/15"
      },
      {
        "text": "Athletics",
        "link": "https://www.olympedia.org/sports/ATH"
      },
      {
        "text": "800 metres, Women",
        "link": "https://www.olympedia.org/results/59982"
      },
      {
        "text": "6 –  7 September 1960"
      }
    ],
    [
      {
        "text": "1960 Summer Olympics",
        "link": "https://www.olympedia.org/editions/15"
      },
      {
        "text": "Athletics",
        "link": "https://www.olympedia.org/sports/ATH"
      },
      {
        "text": "80 metres Hurdles, Women",
        "link": "https://www.olympedia.org/results/59989"
      },
      {
        "text": "31 August –  1 September 1960"
      }
    ],
    [
      {
        "text": "1960 Summer Olympics",
        "link": "https://www.olympedia.org/editions/15"
      },
      {
        "text": "Athletics",
        "link": "https://www.olympedia.org/sports/ATH"
      },
      {
        "text": "4 × 100 metres Relay, Women",
        "link": "https://www.olympedia.org/results/60001"
      },
      {
        "text": "7 –  8 September 1960"
      }
    ],
    [
      {
        "text": "1960 Summer Olympics",
        "link": "https://www.olympedia.org/editions/15"
      },
      {
        "text": "Athletics",
        "link": "https://www.olympedia.org/sports/ATH"
      },
      {
        "text": "High Jump, Women",
        "link": "https://www.olympedia.org/results/60006"
      },
      {
        "text": "7 –  8 September 1960"
      }
    ],
    [
      {
        "text": "1960 Summer Olympics",
        "link": "https://www.olympedia.org/editions/15"
      },
      {
        "text": "Athletics",
        "link": "https://www.olympedia.org/sports/ATH"
      },
      {
        "text": "Long Jump, Women",
        "link": "https://www.olympedia.org/results/60024"
      },
      {
        "text": "31 August 1960"
      }
    ],
    [
      {
        "text": "1960 Summer Olympics",
        "link": "https://www.olympedia.org/editions/15"
      },
      {
        "text": "Athletics",
        "link": "https://www.olympedia.org/sports/ATH"
      },
      {
        "text": "Shot Put, Women",
        "link": "https://www.olympedia.org/results/60036"
      },
      {
        "text": "2 September 1960"
      }
    ],
    [
      {
        "text": "1960 Summer Olympics",
        "link": "https://www.olympedia.org/editions/15"
      },
      {
        "text": "Athletics",
        "link": "https://www.olympedia.org/sports/ATH"
      },
      {
        "text": "Discus Throw, Women",
        "link": "https://www.olympedia.org/results/60048"
      },
      {
        "text": "3 –  5 September 1960"
      }
    ],
    [
      {
        "text": "1960 Summer Olympics",
        "link": "https://www.olympedia.org/editions/15"
      },
      {
        "text": "Athletics",
        "link": "https://www.olympedia.org/sports/ATH"
      },
      {
        "text": "Javelin Throw, Women",
        "link": "https://www.olympedia.org/results/60060"
      },
      {
        "text": "1 September 1960"
      }
    ],
    [
      {
        "text": "1960 Summer Olympics",
        "link": "https://www.olympedia.org/editions/15"
      },
      {
        "text": "Equestrian Jumping",
        "link": "https://www.olympedia.org/sports/EJP"
      },
      {
        "text": "Team, Open",
        "link": "https://www.olympedia.org/results/185198"
      },
      {
        "text": "11 September 1960"
      }
    ]
  ]
}