{
  "biodata": {
    "associated_names": [
      "Stadio Adriatico",
      "Adriatic Stadium",
      "Stadio Adriatico Giovanni Cornacchia (2009-Present)"
    ],
    "place": "Pescara",
    "coordinates": "42.455278,14.229444",
    "coordinates_trust": "Definitely here",
    "year": "1960",
    "season": "Summer",
    "sports": [
      "Football"
    ],
    "opened": "1955",
    "type": "outdoor venue"
  },
  "event_data": [
    [
      {
        "text": "1960 Summer Olympics",
        "link": "https://www.olympedia.org/editions/15"
      },
      {
        "text": "Football",
        "link": "https://www.olympedia.org/sports/FBL"
      },
      {
        "text": "Football, Men",
        "link": "https://www.olympedia.org/results/33739"
      },
      {
        "text": "26 August – 10 September 1960"
      }
    ]
  ]
}