{
  "biodata": {
    "associated_names": [
      "All-England Lawn Tennis & Croquet Club"
    ],
    "place": "Wimbledon, London",
    "coordinates": "51.433744,-0.214064",
    "coordinates_trust": "Definitely here",
    "year": "2012",
    "season": "Summer",
    "sports": [
      "Tennis"
    ],
    "notes": "Different venue then used at the 1908 Olympics, when the club was located at Worple Road.",
    "opened": "1922",
    "seating_capacity": "15000 (centre court) / 30000 (total)",
    "type": "outdoor venue",
    "surface": "Grass"
  },
  "event_data": [
    [
      {
        "text": "2012 Summer Olympics",
        "link": "https://www.olympedia.org/editions/54"
      },
      {
        "text": "Tennis",
        "link": "https://www.olympedia.org/sports/TEN"
      },
      {
        "text": "Singles, Women",
        "link": "https://www.olympedia.org/results/324000"
      },
      {
        "text": "28 July –  5 August 2012"
      }
    ],
    [
      {
        "text": "2012 Summer Olympics",
        "link": "https://www.olympedia.org/editions/54"
      },
      {
        "text": "Tennis",
        "link": "https://www.olympedia.org/sports/TEN"
      },
      {
        "text": "Singles, Men",
        "link": "https://www.olympedia.org/results/324071"
      },
      {
        "text": "28 July –  5 August 2012"
      }
    ],
    [
      {
        "text": "2012 Summer Olympics",
        "link": "https://www.olympedia.org/editions/54"
      },
      {
        "text": "Tennis",
        "link": "https://www.olympedia.org/sports/TEN"
      },
      {
        "text": "Doubles, Men",
        "link": "https://www.olympedia.org/results/324142"
      },
      {
        "text": "28 July –  4 August 2012"
      }
    ],
    [
      {
        "text": "2012 Summer Olympics",
        "link": "https://www.olympedia.org/editions/54"
      },
      {
        "text": "Tennis",
        "link": "https://www.olympedia.org/sports/TEN"
      },
      {
        "text": "Doubles, Women",
        "link": "https://www.olympedia.org/results/324180"
      },
      {
        "text": "28 July –  5 August 2012"
      }
    ],
    [
      {
        "text": "2012 Summer Olympics",
        "link": "https://www.olympedia.org/editions/54"
      },
      {
        "text": "Tennis",
        "link": "https://www.olympedia.org/sports/TEN"
      },
      {
        "text": "Doubles, Mixed",
        "link": "https://www.olympedia.org/results/324218"
      },
      {
        "text": "28 July –  5 August 2012"
      }
    ]
  ]
}